{
	"class" : {
		"codeFontName" : "EstebanLorenzano 10/11/2013 14:06",
		"defaultFontName" : "EstebanLorenzano 10/11/2013 14:34",
		"fontButton:size:" : "EstebanLorenzano 10/11/2013 11:36",
		"fontName" : "EstebanLorenzano 10/11/2013 11:36",
		"fontSourceCodeRow" : "EstebanLorenzano 10/11/2013 12:47",
		"registerFonts:" : "IgorStasenko 10/11/2013 17:21",
		"setSourceCodeFonts:" : "EstebanLorenzano 10/11/2013 14:19",
		"settingsOn:" : "EstebanLorenzano 10/11/2013 12:25",
		"sizeHuge" : "EstebanLorenzano 10/11/2013 12:27",
		"sizeLarge" : "EstebanLorenzano 10/11/2013 12:27",
		"sizeMedium" : "EstebanLorenzano 10/11/2013 12:27",
		"sizeSmall" : "EstebanLorenzano 10/11/2013 11:36",
		"sizeVeryLarge" : "EstebanLorenzano 10/11/2013 12:27",
		"useSourceCode" : "EstebanLorenzano 10/11/2013 11:36",
		"useSourceCode:" : "EstebanLorenzano 10/11/2013 11:36" },
	"instance" : {
		"seeClassSide" : "EstebanLorenzano 10/11/2013 11:36" } }
